ubo_app/.env
ubo_app/__init__.py
ubo_app/_ignore_this_in_back_track.py
ubo_app/_version.py
ubo_app/colors.py
ubo_app/constants.py
ubo_app/display.py
ubo_app/logger.py
ubo_app/main.py
ubo_app/py.typed
ubo_app/service.py
ubo_app/service_thread.py
ubo_app/setup.py
ubo_app/side_effects.py
ubo_app/engines/google_cloud.py
ubo_app/engines/openai.py
ubo_app/engines/abstraction/background_running_mixin.py
ubo_app/engines/abstraction/needs_setup_mixin.py
ubo_app/menu_app/home_page.kv
ubo_app/menu_app/home_page.py
ubo_app/menu_app/menu.py
ubo_app/menu_app/menu_central.py
ubo_app/menu_app/menu_footer.py
ubo_app/menu_app/menu_header.py
ubo_app/menu_app/menu_notification_handler.py
ubo_app/menu_app/notification_info.kv
ubo_app/menu_app/notification_info.py
ubo_app/rpc/README.md
ubo_app/rpc/message_to_object.py
ubo_app/rpc/object_to_message.py
ubo_app/rpc/parent_version.py
ubo_app/rpc/pyproject.toml
ubo_app/rpc/secrets_service.py
ubo_app/rpc/server.py
ubo_app/rpc/store_service.py
ubo_app/rpc/uv.lock
ubo_app/rpc/generator/__init__.py
ubo_app/rpc/generator/_module_transformer.py
ubo_app/rpc/generator/_types.py
ubo_app/rpc/generator/generate_proto.py
ubo_app/rpc/proto/buf.yaml
ubo_app/rpc/proto/package_info/v1/package_info.proto
ubo_app/rpc/proto/secrets/v1/secrets.proto
ubo_app/rpc/proto/store/v1/store.proto
ubo_app/rpc/ubo_bindings/client.py
ubo_app/services/000-audio/audio_manager.py
ubo_app/services/000-audio/constants.py
ubo_app/services/000-audio/reducer.py
ubo_app/services/000-audio/setup.py
ubo_app/services/000-audio/ubo_handle.py
ubo_app/services/000-audio/sounds/add.wav
ubo_app/services/000-audio/sounds/done.wav
ubo_app/services/000-audio/sounds/failure.wav
ubo_app/services/000-audio/sounds/volume.wav
ubo_app/services/000-display/reducer.py
ubo_app/services/000-display/setup.py
ubo_app/services/000-display/ubo_handle.py
ubo_app/services/000-keypad/reducer.py
ubo_app/services/000-keypad/setup.py
ubo_app/services/000-keypad/ubo_handle.py
ubo_app-1.6.0.dist-info/METADATA
ubo_app-1.6.0.dist-info/WHEEL
ubo_app-1.6.0.dist-info/entry_points.txt
ubo_app-1.6.0.dist-info/RECORD
