Metadata-Version: 2.4
Name: ubo-app
Version: 1.6.0
Summary: Ubo main app, running on device initialization. A platform for running other apps.
Author-email: Sassan Haradji <me@sassanh.com>
Maintainer-email: Sassan Haradji <me@sassanh.com>
License-Expression: Apache-2.0
Keywords: home assistance,raspberry pi,rpi,ubo,ubo-pod
Requires-Python: <3.12,>=3.11
Requires-Dist: adafruit-blinka-raspberry-pi5-neopixel==1.0.0rc2; platform_machine == 'aarch64' and sys_platform == 'linux'
Requires-Dist: adafruit-blinka==8.64.0
Requires-Dist: adafruit-circuitpython-aw9523==1.1.12
Requires-Dist: adafruit-circuitpython-busdevice==5.2.13
Requires-Dist: adafruit-circuitpython-connectionmanager==3.1.5
Requires-Dist: adafruit-circuitpython-irremote==5.0.4
Requires-Dist: adafruit-circuitpython-neopixel==6.3.16
Requires-Dist: adafruit-circuitpython-pct2075==1.1.24
Requires-Dist: adafruit-circuitpython-pixelbuf==2.0.8
Requires-Dist: adafruit-circuitpython-register==1.10.4
Requires-Dist: adafruit-circuitpython-requests==4.1.13
Requires-Dist: adafruit-circuitpython-rgb-display==3.14.0
Requires-Dist: adafruit-circuitpython-typing==1.12.1
Requires-Dist: adafruit-circuitpython-veml7700==2.1.3
Requires-Dist: adafruit-platformdetect==3.82.0
Requires-Dist: adafruit-pureio==1.1.11
Requires-Dist: aiofiles==24.1.0
Requires-Dist: aiohappyeyeballs==2.6.1
Requires-Dist: aiohttp==3.12.9
Requires-Dist: aiosignal==1.4.0
Requires-Dist: aiostream==0.6.4
Requires-Dist: annotated-types==0.7.0
Requires-Dist: anyio==4.10.0
Requires-Dist: attrs==25.3.0
Requires-Dist: betterproto[compiler]==2.0.0b7
Requires-Dist: binho-host-adapter==0.1.6
Requires-Dist: black==25.1.0
Requires-Dist: blinker==1.9.0
Requires-Dist: cachetools==5.5.2
Requires-Dist: certifi==2025.8.3
Requires-Dist: cffi==1.17.1
Requires-Dist: charset-normalizer==3.4.3
Requires-Dist: click==8.2.1
Requires-Dist: colorama==0.4.6; sys_platform == 'win32'
Requires-Dist: coloredlogs==15.0.1
Requires-Dist: colorzero==2.0; platform_machine != 'aarch64'
Requires-Dist: dill==0.4.0
Requires-Dist: docker==7.1.0
Requires-Dist: docstring-parser==0.17.0
Requires-Dist: docutils==0.22
Requires-Dist: fasteners==0.19
Requires-Dist: filetype==1.2.0
Requires-Dist: flask==3.1.2
Requires-Dist: flatbuffers==25.2.10
Requires-Dist: frozenlist==1.7.0
Requires-Dist: google-api-core==2.25.1
Requires-Dist: google-auth==2.40.3
Requires-Dist: google-cloud-aiplatform==1.96.0
Requires-Dist: google-cloud-bigquery==3.36.0
Requires-Dist: google-cloud-core==2.4.3
Requires-Dist: google-cloud-resource-manager==1.14.2
Requires-Dist: google-cloud-speech==2.32.0
Requires-Dist: google-cloud-storage==2.19.0
Requires-Dist: google-crc32c==1.7.1
Requires-Dist: google-genai==1.31.0
Requires-Dist: google-resumable-media==2.7.2
Requires-Dist: googleapis-common-protos==1.70.0
Requires-Dist: gpiozero==2.0.1; platform_machine != 'aarch64'
Requires-Dist: grpc-google-iam-v1==0.14.2
Requires-Dist: grpcio-status==1.74.0
Requires-Dist: grpcio==1.74.0
Requires-Dist: grpclib==0.4.8
Requires-Dist: h11==0.16.0
Requires-Dist: h2==4.3.0
Requires-Dist: headless-kivy==0.12.4
Requires-Dist: hpack==4.1.0
Requires-Dist: httpcore==1.0.9
Requires-Dist: httpx==0.28.1
Requires-Dist: humanfriendly==10.0
Requires-Dist: hypercorn==0.17.3
Requires-Dist: hyperframe==6.1.0
Requires-Dist: idna==3.10
Requires-Dist: isort==5.13.2
Requires-Dist: itsdangerous==2.2.0
Requires-Dist: jinja2==3.1.6
Requires-Dist: kivy-deps-angle==0.4.0; sys_platform == 'win32'
Requires-Dist: kivy-deps-glew==0.3.1; sys_platform == 'win32'
Requires-Dist: kivy-deps-sdl2==0.8.0; sys_platform == 'win32'
Requires-Dist: kivy-garden==0.1.5
Requires-Dist: kivy==2.3.1
Requires-Dist: lgpio==0.2.2.0; platform_machine == 'aarch64' and sys_platform == 'linux'
Requires-Dist: markupsafe==3.0.2
Requires-Dist: mpmath==1.3.0
Requires-Dist: multidict==6.6.4
Requires-Dist: mypy-extensions==1.1.0
Requires-Dist: netifaces==0.11.0
Requires-Dist: numpy==1.26.4
Requires-Dist: ollama==0.5.1
Requires-Dist: onnxruntime==1.22.1
Requires-Dist: onnxruntime>=1.22.0; sys_platform == 'linux' and platform_machine == 'aarch64'
Requires-Dist: packaging==25.0
Requires-Dist: pathspec==0.12.1
Requires-Dist: piper-tts==1.3.0
Requires-Dist: platformdirs==4.3.8
Requires-Dist: priority==2.0.0
Requires-Dist: propcache==0.3.2
Requires-Dist: proto-plus==1.26.1
Requires-Dist: protobuf==6.32.0
Requires-Dist: psutil==7.0.0
Requires-Dist: pulsectl==24.12.0
Requires-Dist: pvorca==1.1.1
Requires-Dist: pyalsaaudio==0.11.0; platform_machine == 'aarch64' and sys_platform == 'linux'
Requires-Dist: pyasn1-modules==0.4.2
Requires-Dist: pyasn1==0.6.1
Requires-Dist: pyaudio==0.2.14; platform_machine != 'aarch64' or sys_platform != 'linux'
Requires-Dist: pycparser==2.22
Requires-Dist: pydantic-core==2.33.2
Requires-Dist: pydantic==2.11.7
Requires-Dist: pyftdi==0.57.1
Requires-Dist: pygments==2.19.2
Requires-Dist: pypiwin32==223; sys_platform == 'win32'
Requires-Dist: pypng==0.20220715.0
Requires-Dist: pyreadline3==3.5.4; sys_platform == 'win32'
Requires-Dist: pyserial==3.5
Requires-Dist: python-dateutil==2.9.0.post0
Requires-Dist: python-debouncer==0.1.5
Requires-Dist: python-dotenv==1.1.0
Requires-Dist: python-fake==0.2.0
Requires-Dist: python-immutable==1.2.2
Requires-Dist: python-redux==0.24.1.dev1250523103975755100
Requires-Dist: python-strtobool==1.0.3
Requires-Dist: pyusb==1.3.1
Requires-Dist: pywin32==311; sys_platform == 'win32'
Requires-Dist: pyzbar==0.1.9
Requires-Dist: qrcode==8.2
Requires-Dist: quart==0.20.0
Requires-Dist: requests==2.32.5
Requires-Dist: rpi-lgpio==0.6; platform_machine == 'aarch64' and sys_platform == 'linux'
Requires-Dist: rpi-ws281x==5.0.0; platform_machine == 'aarch64'
Requires-Dist: rsa==4.9.1
Requires-Dist: sdbus-networkmanager==2.0.0; platform_machine == 'aarch64'
Requires-Dist: sdbus==0.14.0; platform_machine == 'aarch64'
Requires-Dist: sentry-sdk==2.29.1
Requires-Dist: setuptools==80.9.0; platform_machine != 'aarch64'
Requires-Dist: shapely==2.1.1
Requires-Dist: simpleaudio==1.0.4
Requires-Dist: six==1.17.0
Requires-Dist: sniffio==1.3.1
Requires-Dist: soxr==0.5.0.post1
Requires-Dist: srt==3.5.3
Requires-Dist: sympy==1.14.0
Requires-Dist: sysv-ipc==1.1.0; platform_machine != 'mips' and sys_platform == 'linux'
Requires-Dist: tenacity==9.1.2
Requires-Dist: tqdm==4.67.1
Requires-Dist: typing-extensions==4.14.1
Requires-Dist: typing-inspection==0.4.1
Requires-Dist: ubo-app-raw-bindings==1.6.0
Requires-Dist: ubo-gui==0.13.17
Requires-Dist: urllib3==2.5.0
Requires-Dist: vosk==0.3.44
Requires-Dist: websockets==15.0.1
Requires-Dist: werkzeug==3.1.3
Requires-Dist: wsproto==1.2.0
Requires-Dist: yarl==1.20.1
Provides-Extra: test-investigation
Requires-Dist: graphviz>=0.20.3; extra == 'test-investigation'
Requires-Dist: objgraph>=3.6.2; extra == 'test-investigation'
